setup.py
rezene/__init__.py
rezene/models.py
rezene.egg-info/PKG-INFO
rezene.egg-info/SOURCES.txt
rezene.egg-info/dependency_links.txt
rezene.egg-info/requires.txt
rezene.egg-info/top_level.txt
tests/__init__.py
tests/test_decl.py