Metadata-Version: 1.1
Name: rezene
Version: 0.1a1
Summary: An alternative API for lxml
Home-page: https://github.com/propars/rezene
Author: Cengiz Kaygusuz
Author-email: cengiz@propars.net
License: UNKNOWN
Keywords: lxml xml data
Platform: UNKNOWN
Classifier: Development Status :: 3 - Alpha
